pycounts_junigord/__init__.py
pycounts_junigord/plotting.py
pycounts_junigord/pycounts_junigord.py
pycounts_junigord-0.1.0.dist-info/LICENSE
pycounts_junigord-0.1.0.dist-info/WHEEL
pycounts_junigord-0.1.0.dist-info/METADATA
pycounts_junigord-0.1.0.dist-info/RECORD
