Metadata-Version: 2.1
Name: pycounts-junigord
Version: 0.1.0
Summary: testing package creation
License: MIT
Author: Julien Gordon
Requires-Python: >=3.9,<4.0
Classifier: License :: OSI Approved :: MIT License
Classifier: Programming Language :: Python :: 3
Classifier: Programming Language :: Python :: 3.10
Classifier: Programming Language :: Python :: 3.9
Requires-Dist: matplotlib (>=3.5.1,<4.0.0)
